datalearn19intro/__init__.py
datalearn19intro/dataloader.py
datalearn19intro-0.0.5.dist-info/METADATA
datalearn19intro-0.0.5.dist-info/RECORD
datalearn19intro-0.0.5.dist-info/WHEEL
datalearn19intro-0.0.5.dist-info/top_level.txt
