Metadata-Version: 2.1
Name: datalearn19intro
Version: 0.0.5
Summary: Helper code for DataLearn 2019 ML Intro Workshop.
Home-page: https://github.com/DataHackIL/DataLearn-ML-Intro-2019
Author: Shay Palachy
Author-email: shay.palachy@gmail.com
License: MIT
Platform: UNKNOWN
Classifier: Development Status :: 4 - Beta
Classifier: License :: OSI Approved :: MIT License
Classifier: Programming Language :: Python
Classifier: Programming Language :: Python :: 3.5
Classifier: Programming Language :: Python :: 3.6
Classifier: Programming Language :: Python :: 3.7
Classifier: Topic :: Software Development :: Libraries
Classifier: Topic :: Software Development :: Libraries :: Python Modules
Classifier: Intended Audience :: Developers
Requires-Python: >=3.5
Requires-Dist: numpy
Requires-Dist: pandas
